{"0": {"status": true, "place_id": "ChIJN7CTMebvcTQRvlAZ2AQdHCE"}, "1": {"status": true, "place_id": "ChIJSZUvicHvcTQR5lnmGDh3-3o"}, "2": {"status": true, "place_id": "ChIJv81sDu7vcTQRlaLAiQFEjTo"}, "3": {"status": true, "place_id": "ChIJ-wE38urvcTQRgUqp_XdXNUM"}, "4": {"status": true, "place_id": "ChIJ0bff4WXlcTQRivCO48fEB7A"}, "5": {"status": true, "place_id": "ChIJ1z8DOHDlcTQRvxYu08n0Qsg"}, "6": {"status": true, "place_id": "ChIJL3dkmHDlcTQRqnWKQRph2m4"}, "7": {"status": true, "place_id": "ChIJTX0rfazhcTQR6RQL0vAEfks"}, "8": {"status": true, "place_id": "ChIJP4H2J_PvcTQRYxgSRB8slsU"}, "9": {"status": true, "place_id": "ChIJX7D1gI7vcTQRt8h_xD7qspE"}, "10": {"status": true, "place_id": "ChIJC7r1gI7vcTQR96ToMXYm8xU"}, "11": {"status": true, "place_id": "ChIJ3wQsapLvcTQR8U-xyenjTLg"}, "12": {"status": true, "place_id": "ChIJ_____4rvcTQR-4EWAuze-W8"}, "13": {"status": true, "place_id": "ChIJX7D1gI7vcTQRhyTWfCfrJEI"}, "14": {"status": true, "place_id": "ChIJFT5G03jlcTQRlPwNaXvpB7Y"}, "15": {"status": true, "place_id": "ChIJy2jLsPTvcTQR044dYLYFJ-M"}, "16": {"status": true, "place_id": "ChIJx5KyZmblcTQRHtDZWLT9r_Y"}, "17": {"status": true, "place_id": "ChIJzQgNYPTvcTQRP97_pXtgqT8"}, "18": {"status": true, "place_id": "ChIJf-_c9XDlcTQRuEHHh1Oceps"}, "19": {"status": true, "place_id": "ChIJD5LiEYfvcTQRgJ-x5UtuPx4"}, "20": {"status": true, "place_id": "ChIJTQMGFuvvcTQRDfGo_VUyFF0"}, "21": {"status": true, "place_id": "ChIJfSoEHYvvcTQRX9KP0xkvOYA"}, "22": {"status": true, "place_id": "ChIJ92ndTIfvcTQRJSXATkYPImc"}, "23": {"status": true, "place_id": "ChIJdZvSufPvcTQReLjZ4EC3KM4"}, "24": {"status": true, "place_id": "ChIJBXzNXgXhcTQR1jBvIuRtpVQ"}, "25": {"status": true, "place_id": "ChIJs2CBNn_lcTQRGqq3yQk_pII"}, "26": {"status": true, "place_id": "ChIJbWzFJXjlcTQRYor4veC-HJE"}, "27": {"status": true, "place_id": "ChIJLe7zZOrvcTQR7Xy65j-k79o"}, "28": {"status": true, "place_id": "ChIJAUvAL3jlcTQRKbM0WWN-iJI"}, "29": {"status": true, "place_id": "ChIJKQSab2blcTQR5iskLam5Eo4"}, "30": {"status": true, "place_id": "ChIJwzKXwsLvcTQRR3wTvH5DzH4"}, "31": {"status": true, "place_id": "ChIJpQCHxMHvcTQRIRJ3iO4NT0k"}, "32": {"status": true, "place_id": "ChIJHe2o3YfvcTQRjvRsZO6y8Qo"}, "33": {"status": true, "place_id": "ChIJParDx-fvcTQR_ktdY61JhwE"}, "34": {"status": true, "place_id": "ChIJAU4EZmblcTQRRJlUNwNGqcE"}, "35": {"status": true, "place_id": "ChIJOeGqj8HvcTQRd2A48LEGT4Q"}, "36": {"status": true, "place_id": "ChIJdeLxEl7lcTQRGYJMDYGIanE"}, "37": {"status": true, "place_id": "ChIJO6dPtV_lcTQRAKpg1-AVkV0"}}